{
  "anti_claim": "The Python lens is a public-safe path and route-readiness read-model. It does not execute Python, infer correctness, export source bodies, mutate source, call providers, or claim production/package quality.",
  "authority_ceiling": {
    "private_data_equivalence_authorized": false,
    "provider_calls_authorized": false,
    "release_authorized": false,
    "source_bodies_exported": false,
    "source_files_mutated": false,
    "static_analysis_authority_claim": false
  },
  "body_redacted": true,
  "command": "microcosm python-lens <project>",
  "created_at": "2026-05-22T13:36:50+00:00",
  "event_id": "evt_0450",
  "evidence_ref": ".microcosm/evidence/python_lens.json",
  "evidence_replacement": {
    "append_only_event_history_ref": ".microcosm/events.jsonl",
    "policy": "stable_ref_latest_body",
    "previous_sha256": "857369d03146ece2568161c519a00dbbea1fc38b02aa3275003b13c9a51bc3ec",
    "replacement_recorded": true,
    "stable_ref": ".microcosm/evidence/python_lens.json"
  },
  "lens_id": "project_python_route_lens",
  "missing_check_count": 1,
  "package_roots": [
    "src/app"
  ],
  "passing_check_count": 4,
  "path_rows": [
    {
      "absolute_import_count": 0,
      "body_redacted": true,
      "bytes": 10,
      "catalog_role": "source",
      "has_main_guard": false,
      "path": "src/app/__init__.py",
      "python_role": "package_init",
      "relative_import_count": 0
    },
    {
      "absolute_import_count": 1,
      "body_redacted": true,
      "bytes": 72,
      "catalog_role": "test",
      "has_main_guard": false,
      "path": "tests/test_smoke.py",
      "python_role": "test_module",
      "relative_import_count": 0
    }
  ],
  "project_id": "launch_compression_project",
  "project_ref": ".",
  "public_claim": "Microcosm exposes Python project route readiness as path-level metadata without source bodies, provider calls, or source mutation.",
  "python_file_count": 2,
  "readiness_checks": [
    {
      "check_id": "pyproject_declared",
      "grounded_refs": [
        "pyproject.toml"
      ],
      "status": "pass"
    },
    {
      "check_id": "python_source_visible",
      "grounded_refs": [
        "src/app"
      ],
      "status": "pass"
    },
    {
      "check_id": "python_tests_visible",
      "grounded_refs": [
        "tests/test_smoke.py"
      ],
      "status": "pass"
    },
    {
      "check_id": "python_entrypoint_visible",
      "grounded_refs": [],
      "status": "missing"
    },
    {
      "check_id": "python_package_roots_visible",
      "grounded_refs": [
        "src/app"
      ],
      "status": "pass"
    }
  ],
  "ready_route_count": 3,
  "receipts_are_drilldown_evidence": true,
  "release_authorized": false,
  "route_rows": [
    {
      "authority": "project_local_python_route_lens_not_static_analysis_authority",
      "grounded_refs": [
        "pyproject.toml"
      ],
      "provider_calls_authorized": false,
      "readiness": "pass",
      "route_id": "python_package_metadata_route",
      "source_mutation_authorized": false,
      "title": "Inspect Python package metadata"
    },
    {
      "authority": "project_local_python_route_lens_not_static_analysis_authority",
      "grounded_refs": [
        "src/app"
      ],
      "provider_calls_authorized": false,
      "readiness": "pass",
      "route_id": "python_source_core_route",
      "source_mutation_authorized": false,
      "title": "Inspect Python source core"
    },
    {
      "authority": "project_local_python_route_lens_not_static_analysis_authority",
      "grounded_refs": [
        "tests/test_smoke.py"
      ],
      "provider_calls_authorized": false,
      "readiness": "pass",
      "route_id": "python_test_behavior_route",
      "source_mutation_authorized": false,
      "title": "Inspect Python behavior tests"
    },
    {
      "authority": "project_local_python_route_lens_not_static_analysis_authority",
      "grounded_refs": [],
      "provider_calls_authorized": false,
      "readiness": "missing",
      "route_id": "python_entrypoint_route",
      "source_mutation_authorized": false,
      "title": "Inspect Python entrypoint scripts"
    }
  ],
  "schema_version": "microcosm_project_python_lens_v1",
  "standard_refs": [
    "standards/std_microcosm_route_decision.json",
    "standards/std_microcosm_source_capsule.json",
    "standards/std_microcosm_evidence_cell.json"
  ],
  "state_file_ref": ".microcosm/python_lens.json",
  "state_ref": ".microcosm",
  "status": "pass"
}
